MANIFEST.in
README
setup.py
data/hvr1_motifs.yaml
data/motifs.shelved
oldowan/__init__.py
oldowan.mitotype.egg-info/PKG-INFO
oldowan.mitotype.egg-info/SOURCES.txt
oldowan.mitotype.egg-info/dependency_links.txt
oldowan.mitotype.egg-info/entry_points.txt
oldowan.mitotype.egg-info/namespace_packages.txt
oldowan.mitotype.egg-info/not-zip-safe
oldowan.mitotype.egg-info/requires.txt
oldowan.mitotype.egg-info/top_level.txt
oldowan/mitotype/VERSION
oldowan/mitotype/__init__.py
oldowan/mitotype/commandline.py
oldowan/mitotype/matcher.py
oldowan/mitotype/motif.py
oldowan/mitotype/network.py
oldowan/mitotype/prevalidate.py
oldowan/mitotype/externals/__init__.py
oldowan/mitotype/externals/immutable_dict.py