Metadata-Version: 1.0
Name: oldowan.mitotype
Version: 1.0.1
Summary: Utilities to identify human mtDNA haplotypes.
